h5utils/__init__.py
h5utils/h5tovts.py
h5utils/h5utils.py
h5utils/constants/__init__.py
h5utils/constants/physcon.py
h5utils/data/lattice-cartesian-epsilon.h5
h5utils/data/lattice-non-cartesian-epsilon.h5
h5utils/data/lattice-non-cartesian.ctl
h5utils/data/lattice-visualization-non-cartesian.pvsm
h5utils/data/lattice-visualization.ctl
h5utils-0.0.4.dist-info/LICENSE
h5utils-0.0.4.dist-info/METADATA
h5utils-0.0.4.dist-info/WHEEL
h5utils-0.0.4.dist-info/entry_points.txt
h5utils-0.0.4.dist-info/top_level.txt
h5utils-0.0.4.dist-info/RECORD
