Metadata-Version: 2.1
Name: h5utils
Version: 0.0.4
Summary: Utilities to work with HDF5 files.       Notably includes h5tovts, which converts HDF5 files to structured VTK files       for visualization with VTK-aware programs.
Home-page: https://github.com/mtav/h5utils
Author: Mike Taverne
Author-email: Mike.Taverne@bristol.ac.uk
License: UNKNOWN
Platform: UNKNOWN
Classifier: Programming Language :: Python :: 3
Classifier: License :: OSI Approved :: GNU General Public License v3 or later (GPLv3+)
Classifier: Operating System :: OS Independent
Requires-Python: >=3.6
Requires-Dist: numpy
Requires-Dist: vtk
Requires-Dist: h5py
